{
  "items": [
    {"id":"nydri","name":"Nydri (Dimosari) Waterfalls","name_gr":"Καταρράκτες Νυδριού (Δημοσάρη)","area":"Nydri","area_gr":"Νυδρί","type":"Nature","short":"A pleasant short hike to small waterfalls. Not recommended during summer.","short_gr":"Ευχάριστη σύντομη πεζοπορία προς μικρούς καταρράκτες. Δεν προτείνεται στο αποκορύφωμα του καλοκαιριού.","tips":["Bring water shoes","Easy family-friendly trail"],"image":"dataset/images/attractions/waterfall.jpg","mapLink":"https://www.google.com/maps/place/Parking+Nidri+Waterfall/@38.7230423,20.6881995,16z/data=!4m6!3m5!1s0x135db58b6001aa8d:0x7d0599fbdcb77f18!8m2!3d38.7225814!4d20.6900604!16s%2Fg%2F11h57hbkt5?entry=ttu&g_ep=EgoyMDI2MDQxMy4wIKXMDSoASAFQAw%3D%3D"},
    {"id":"faneromeni","name":"Faneromeni Monastery","name_gr":"Μονή Φανερωμένης","area":"Lefkada Town","area_gr":"Πόλη Λευκάδας","type":"Monasteries","short":"Historic monastery with scenic views.","short_gr":"Ιστορικό μοναστήρι με όμορφη θέα.","tips":["Modest dress recommended","Check opening times"],"image":"dataset/images/attractions/faneromeni.jpg","mapLink":"https://www.google.com/maps?q=Faneromeni+Monastery"},
    {"id":"agia-mavra","name":"Agia Mavra Castle","name_gr":"Κάστρο Αγίας Μαύρας","area":"South Lefkada","area_gr":"Νότια Λευκάδα","type":"History","short":"Ruins with coastal views and a peaceful atmosphere.","short_gr":"Ερείπια με θέα στη θάλασσα και ήρεμη ατμόσφαιρα.","tips":["Rough access road","Wear sturdy shoes"],"image":"dataset/images/attractions/castro.png","mapLink":"https://www.google.com/maps?q=Agia+Mavra+Castle"},
    {"id":"lefkada-town","name":"Lefkada Town Old Harbour","name_gr":"Παλιό Λιμάνι Λευκάδας","area":"Lefkada Town","area_gr":"Πόλη Λευκάδας","type":"Landmarks","short":"Picturesque harbour area with shops and cafés.","short_gr":"Γραφική λιμενική περιοχή με μαγαζιά και καφέ.","tips":["Nice for evening walks","Try local ice cream"],"image":"dataset/images/attractions/bridge.jpg","mapLink":"https://www.google.com/maps/place/%CE%9E%CF%8D%CE%BB%CE%B9%CE%BD%CE%B7+%CE%93%CE%AD%CF%86%CF%85%CF%81%CE%B1+%CE%9B%CE%B5%CF%85%CE%BA%CE%AC%CE%B4%CE%B1%CF%82/@38.8356688,20.7096614,17z/data=!3m1!4b1!4m6!3m5!1s0x135c49ffa217facb:0x96352f9e3dec0d72!8m2!3d38.8356688!4d20.7096614!16s%2Fg%2F1222z85v?entry=ttu&g_ep=EgoyMDI2MDQxMy4wIKXMDSoASAFQAw%3D%3D"},
    {"id":"arch-museum","name":"Archaeological Museum","name_gr":"Αρχαιολογικό Μουσείο","area":"Lefkada Town","area_gr":"Πόλη Λευκάδας","type":"Museums","short":"Museum showcasing artifacts and local history from ancient times.","short_gr":"Μουσείο με αρχαία αντικείμενα και τοπική ιστορία.","tips":["Check opening hours","Guided tours available"],"image":"dataset/images/attractions/archaeological_museum.jpg","mapLink":"https://www.google.com/maps?q=Archaeological+Museum+Lefkada"},
    {"id":"folklore-karya","name":"Folklore Museum of Karya","name_gr":"Μουσείο Λαϊκής Τέχνης Καρυάς","area":"Karya","area_gr":"Καρυά","type":"Museums","short":"Traditional Lefkadian crafts and folk heritage displays.","short_gr":"Παράδοση και τοπικές δημιουργίες από την Λευκάδα.","tips":["Beautiful village setting","Support local artisans"],"image":"dataset/images/attractions/karya_museum.jpg","mapLink":"https://www.google.com/maps?q=Folklore+Museum+Karya+Lefkada"},
    {"id":"sikelianos-museum","name":"Angelos Sikelianos Museum","name_gr":"Μουσείο Αγγέλου Σικελιανού","area":"Lefkada Town","area_gr":"Πόλη Λευκάδας","type":"Museums","short":"Museum dedicated to the famous Greek poet and his life.","short_gr":"Μουσείο αφιερωμένο στο διάσημο έλληνα ποιητή.","tips":["Learn about Greek literature","Beautiful old house"],"image":"dataset/images/attractions/sikelianos.jpg","mapLink":"https://www.google.com/maps?q=Angelos+Sikelianos+Museum+Lefkada"},
    {"id":"melissa-gorge","name":"Melissa Gorge","name_gr":"Φαράγγι Μέλισσας","area":"Central Lefkada","area_gr":"Κεντρική Λευκάδα","type":"Nature","short":"Beautiful mountain gorge with hiking trails and natural beauty.","short_gr":"Όμορφο φαράγγι με μονοπάτια πεζοπορίας και φυσική ομορφιά.","tips":["Bring proper hiking shoes","Take plenty of water"],"image":"dataset/images/attractions/melissa_gorge.jpg","mapLink":"https://www.google.com/maps?q=Melissa+Gorge+Lefkada"},
    {"id":"papanikolis-cave","name":"Papanikolis Sea Cave","name_gr":"Σπηλιά Παπανικόλη","area":"West Lefkada","area_gr":"Δυτική Λευκάδα","type":"Nature","short":"Historic sea cave accessible by boat, famous from WWII history.","short_gr":"Θαλάσσια σπηλιά προσβάσιμη με βάρκα, διάσημη από WWII.","tips":["Boat tours available","Bring camera for photos"],"image":"dataset/images/attractions/papanikolis.jpg","mapLink":"https://www.google.com/maps?q=Papanikolis+Sea+Cave"},
    {"id":"cape-lefkatas","name":"Cape Lefkatas & Lighthouse","name_gr":"Ακρωτήριο Λευκάτα & Φάρος","area":"Southwest Lefkada","area_gr":"Νοτιοδυτική Λευκάδα","type":"Landmarks","short":"Historic cape with lighthouse offering spectacular views and sunset.","short_gr":"Ιστορικό ακρωτήριο με φάρο και θεαματική θέα στο ηλιοβασίλεμα.","tips":["Go for sunset","Bring comfortable shoes"],"image":"dataset/images/attractions/lefkatas.jpg","mapLink":"https://www.google.com/maps?q=Cape+Lefkatas+Lighthouse"},
    {"id":"profitis-ilias","name":"Profitis Ilias Mountain","name_gr":"Προφήτης Ηλίας","area":"South Lefkada","area_gr":"Νότια Λευκάδα","type":"Landmarks","short":"Mountain with panoramic views and hiking opportunities.","short_gr":"Βουνό με πανοραμική θέα και δυνατότητες πεζοπορίας.","tips":["Early morning hike recommended","Clear weather for best views"],"image":"dataset/images/attractions/profitis_ilias.jpg","mapLink":"https://www.google.com/maps/place/%CE%A0%CF%81%CE%BF%CF%86%CE%AE%CF%84%CE%B7%CF%82+%CE%97%CE%BB%CE%AF%CE%B1%CF%82/@38.6888979,20.636122,16z/data=!4m15!1m8!3m7!1s0x135db4213e192ced:0xecc59cb003617c73!2zzpHOsy4gzpfOu86vzrHPgiAzMTAgODIsIM6VzrvOu86szrTOsQ!3b1!8m2!3d38.6892814!4d20.6465443!16zL20vMGY3emN0!3m5!1s0x135db7990dc1ae27:0x63c441ce810208fe!8m2!3d38.685747!4d20.6409144!16s%2Fg%2F11fn0l24fn?entry=ttu&g_ep=EgoyMDI2MDQxMy4wIKXMDSoASAFQAw%3D%3D"}
  ]
}
